obsidian/__init__.py
obsidian/acquisition/__init__.py
obsidian/acquisition/botorch.py
obsidian/acquisition/config.py
obsidian/acquisition/custom.py
obsidian/campaign/__init__.py
obsidian/campaign/analysis.py
obsidian/campaign/campaign.py
obsidian/campaign/explainer.py
obsidian/config.py
obsidian/constraints/__init__.py
obsidian/constraints/base.py
obsidian/constraints/config.py
obsidian/constraints/input.py
obsidian/constraints/output.py
obsidian/dash/__init__.py
obsidian/dash/infobar.py
obsidian/dash/inputs_config.py
obsidian/dash/inputs_data.py
obsidian/dash/optimize.py
obsidian/dash/plots.py
obsidian/dash/predict.py
obsidian/dash/utils.py
obsidian/exceptions.py
obsidian/experiment/__init__.py
obsidian/experiment/benchmark/__init__.py
obsidian/experiment/benchmark/geometric.py
obsidian/experiment/benchmark/optithon.py
obsidian/experiment/design.py
obsidian/experiment/simulator.py
obsidian/experiment/utils.py
obsidian/objectives/__init__.py
obsidian/objectives/base.py
obsidian/objectives/config.py
obsidian/objectives/custom.py
obsidian/objectives/scalarize.py
obsidian/objectives/sequence.py
obsidian/optimizer/__init__.py
obsidian/optimizer/base.py
obsidian/optimizer/bayesian.py
obsidian/parameters/__init__.py
obsidian/parameters/base.py
obsidian/parameters/config.py
obsidian/parameters/continuous.py
obsidian/parameters/discrete.py
obsidian/parameters/param_space.py
obsidian/parameters/targets.py
obsidian/parameters/transforms.py
obsidian/parameters/utils.py
obsidian/plotting/__init__.py
obsidian/plotting/branding.py
obsidian/plotting/mpl.py
obsidian/plotting/plotly.py
obsidian/plotting/shap.py
obsidian/surrogates/__init__.py
obsidian/surrogates/base.py
obsidian/surrogates/botorch.py
obsidian/surrogates/config.py
obsidian/surrogates/custom_GP.py
obsidian/surrogates/custom_torch.py
obsidian/surrogates/utils.py
obsidian/tests/__init__.py
obsidian/tests/default_campaign_MOO.json
obsidian/tests/default_campaign_SOO.json
obsidian/tests/param_configs.py
obsidian_apo-0.8.6.dist-info/LICENSE
obsidian_apo-0.8.6.dist-info/LICENSES_THIRD_PARTY
obsidian_apo-0.8.6.dist-info/METADATA
obsidian_apo-0.8.6.dist-info/WHEEL
obsidian_apo-0.8.6.dist-info/RECORD
