Metadata-Version: 2.3
Name: obsidian-apo
Version: 0.8.6
Summary: Automated experiment design and black-box optimization
Keywords: optimization,experiment design,Bayesian optimization,process development,APO,DOE
Author: Kevin Stone
Author-email: kevin.stone38@gmail.com
Requires-Python: >=3.10,<4.0
Classifier: Development Status :: 4 - Beta
Classifier: License :: OSI Approved :: GNU General Public License v3 (GPLv3)
Classifier: Operating System :: OS Independent
Classifier: Programming Language :: Python :: 3
Classifier: Programming Language :: Python :: 3.10
Classifier: Programming Language :: Python :: 3.11
Classifier: Programming Language :: Python :: 3.12
Classifier: Programming Language :: Python :: 3.13
Provides-Extra: app
Provides-Extra: dev
Provides-Extra: docs
Requires-Dist: botorch (>=0.11.1,<0.12.0)
Requires-Dist: dash (>=2.17.1,<3.0.0) ; extra == "app"
Requires-Dist: dash-bootstrap-components (>=1.6.0,<2.0.0) ; extra == "app"
Requires-Dist: dash-daq (>=0.5.0,<0.6.0) ; extra == "app"
Requires-Dist: flake8 (>=7.1.0,<8.0.0) ; extra == "dev"
Requires-Dist: flask (>=3.0.3,<4.0.0) ; extra == "app"
Requires-Dist: gpytorch (>=1.11,<2.0)
Requires-Dist: ipykernel (>=6.29.4,<7.0.0) ; extra == "dev"
Requires-Dist: jupyterlab (>=4.2.2,<5.0.0) ; extra == "dev"
Requires-Dist: linkify-it-py (>=2.0.3,<3.0.0) ; extra == "docs"
Requires-Dist: matplotlib (>=3.9.0,<4.0.0)
Requires-Dist: myst-parser (>=3.0.1,<4.0.0) ; extra == "docs"
Requires-Dist: numpy (>=1.26,<2.0)
Requires-Dist: pandas (>=2.2.2,<3.0.0)
Requires-Dist: plotly (>=5.22.0,<6.0.0)
Requires-Dist: pydata-sphinx-theme (>=0.15.4,<0.16.0) ; extra == "docs"
Requires-Dist: pytest (>=8.2.2,<9.0.0) ; extra == "dev"
Requires-Dist: pytest-cov (>=5.0.0,<6.0.0) ; extra == "dev"
Requires-Dist: pyyaml (>=6.0.1,<7.0.0)
Requires-Dist: scikit-learn (>=1.5.1,<2.0.0) ; extra == "dev"
Requires-Dist: scipy (>=1.13.1,<2.0.0)
Requires-Dist: shap (>=0.45.1,<0.46.0)
Requires-Dist: sphinx (>=7.3.7,<8.0.0) ; extra == "docs"
Requires-Dist: torch (==2.3.0)
Requires-Dist: xlrd (>=2.0.1,<3.0.0) ; extra == "dev"
Project-URL: Changelog, https://msdllcpapers.github.io/obsidian/stubs/changelog.html
Project-URL: Documentation, https://msdllcpapers.github.io/obsidian/stubs/api_docs.html
Project-URL: Homepage, https://msdllcpapers.github.io/obsidian/
Project-URL: Repository, https://github.com/MSDLLCpapers/obsidian/
